semantic_compiler_core/__init__.py
semantic_compiler_core/api.py
semantic_compiler_core/rlang_runtime.py
semantic_compiler_core/sir_model.py
semantic_compiler_core/sir_to_rlang.py
semantic_compiler_core/sir_validator.py
semantic_compiler_core/version.py
semantic_compiler_core-0.2.8.dist-info/METADATA
semantic_compiler_core-0.2.8.dist-info/WHEEL
semantic_compiler_core-0.2.8.dist-info/top_level.txt
semantic_compiler_core-0.2.8.dist-info/RECORD
