Metadata-Version: 2.4
Name: semantic-compiler-core
Version: 0.2.8
Summary: Deterministic semantic compiler core: SIR → RLang → ProofBundle with stable hashes.
Author-email: Kushagra Bhatnagar <kushagra.bhatnagar@example.com>
License: MIT
Project-URL: Homepage, https://github.com/kushagrab21/Compiler_new
Project-URL: Source, https://github.com/kushagrab21/Compiler_new
Project-URL: Issues, https://github.com/kushagrab21/Compiler_new/issues
Keywords: compiler,deterministic,proofs,hashes,rlang,bor
Classifier: Programming Language :: Python :: 3
Classifier: Operating System :: OS Independent
Requires-Python: >=3.9
Requires-Dist: rlang-compiler>=0.2.4
